mbgui/__init__.py
mbgui/__main__.py
mbgui/executor.py
mbgui/main.py
mbgui/main.ui
mbgui/mblaze.py
mbgui/icons/eye-off-16.png
mbgui/icons/file-16.png
mbgui/icons/flag-16.png
mbgui/icons/folder-16.png
mbgui/icons/inbox-16.png
mbgui/icons/mail-16.png
mbgui/icons/trash-16.png
mbgui-0.1.3.dist-info/LICENSE
mbgui-0.1.3.dist-info/METADATA
mbgui-0.1.3.dist-info/WHEEL
mbgui-0.1.3.dist-info/entry_points.txt
mbgui-0.1.3.dist-info/top_level.txt
mbgui-0.1.3.dist-info/RECORD
