Metadata-Version: 2.1
Name: mbgui
Version: 0.1.3
Summary: Maildir GUI based on mblaze
Home-page: https://github.com/bozokopic/mbgui
License: GPLv3
Platform: UNKNOWN
Classifier: Programming Language :: Python :: 3
Classifier: License :: OSI Approved :: GNU General Public License v3 (GPLv3)
License-File: LICENSE
Requires-Dist: PySide6
